{
	"backtraceGraph" : 
	{
		"commands" : 
		[
			"install"
		],
		"files" : 
		[
			"external/mahi-gui/3rdparty/glfw/src/CMakeLists.txt"
		],
		"nodes" : 
		[
			{
				"file" : 0
			},
			{
				"command" : 0,
				"file" : 0,
				"line" : 247,
				"parent" : 0
			}
		]
	},
	"installers" : 
	[
		{
			"backtrace" : 1,
			"component" : "Unspecified",
			"destination" : "lib",
			"paths" : 
			[
				"external/mahi-gui/3rdparty/glfw/src/libglfw3.a"
			],
			"targetId" : "glfw::@7b16a66fbb5a5abea0a4",
			"targetIndex" : 3,
			"type" : "target"
		}
	],
	"paths" : 
	{
		"build" : "external/mahi-gui/3rdparty/glfw/src",
		"source" : "external/mahi-gui/3rdparty/glfw/src"
	}
}
